{"is_source_file": true, "format": "JavaScript/React", "description": "React component implementing an order tracking screen, displaying order status steps, an order ID, and navigation buttons.", "external_files": ["../../components/atoms/Button", "react", "react-router-dom"], "external_methods": ["useParams", "useNavigate"], "published": ["OrderTracking"], "classes": [], "methods": [{"name": "OrderTracking()", "description": "React functional component rendering order progress status, order ID, and action buttons.", "scope": "", "scopeKind": ""}], "calls": ["useParams", "useNavigate", "navigate", "steps.map"], "search-terms": ["OrderTracking", "react-router-dom", "order progress", "orderId", "React component", "order screen", "order statuses", "Back to Home", "Contact Driver"], "state": 2, "file_id": 31, "knowledge_revision": 66, "git_revision": "", "ctags": [{"_type": "tag", "name": "OrderTracking", "path": "/home/kavia/workspace/code-generation/future-ready-web-application-13008-13017/react_js_frontend/src/screens/order/OrderTracking.js", "pattern": "/^export default function OrderTracking() {$/", "language": "JavaScript", "kind": "function", "signature": "()"}], "hash": "e860201e7ad0a99a9df98c09b2f8b2de", "format-version": 4, "code-base-name": "react_js_frontend", "filename": "react_js_frontend/src/screens/order/OrderTracking.js", "revision_history": [{"66": ""}]}